timeoff/__init__.py
timeoff/_version.py
timeoff/api.py
timeoff/commands.py
timeoff/config.py
timeoff/exceptions.py
timeoff/prompt.py
timeoff/update.py
timeoff/util.py
timeoff/model/__init__.py
timeoff/model/base.py
timeoff/model/entry.py
timeoff/model/policy.py
timeoff/model/schedule.py
timeoff-0.0.6.dist-info/LICENSE
timeoff-0.0.6.dist-info/METADATA
timeoff-0.0.6.dist-info/WHEEL
timeoff-0.0.6.dist-info/entry_points.txt
timeoff-0.0.6.dist-info/top_level.txt
timeoff-0.0.6.dist-info/RECORD
