Metadata-Version: 2.1
Name: timeoff
Version: 0.0.6
Summary: Track vacation hours accrued.
Author-email: Tiffany Huang <hello@tifa.io>
License: MIT
Project-URL: Homepage, https://github.com/tifa/timeoff
Keywords: time off,vacation,pto
Classifier: Development Status :: 2 - Pre-Alpha
Classifier: Environment :: Console
Classifier: Intended Audience :: Developers
Classifier: License :: OSI Approved :: MIT License
Classifier: Natural Language :: English
Classifier: Programming Language :: Python :: 3 :: Only
Classifier: Programming Language :: Python :: 3.8
Requires-Python: >=3.8
License-File: LICENSE
Requires-Dist: prompt-toolkit ==1.0.14
Requires-Dist: tabulate ==0.9.0
